[
		{
			"_id": "1",
			"sura": "1",
			"para": "1",
			"verses": "০",
			"names": "بِسۡمِ ٱللَّهِ ٱلرَّحۡمَٰنِ ٱلرَّحِيمِ",
			"number": "",
			"verses_PDMS": "بِسۡمِ ٱللَّهِ ٱلرَّحۡمَٰنِ ٱلرَّحِيمِ",
			"index": "1",
			"name": "আল্লাহ্‌র নামে আরম্ভ, যিনি পরম দয়ালু, করুণাময় (১)",
			"en_kanzulimaan": "Allah - beginning with the name of - the Most Gracious, the Most Merciful.",
			"ur_kanzulimaan": "Allah - beginning with the name of - the Most Gracious, the Most Merciful.",
			"id": 1,
			"text": "بِسۡمِ ٱللَّهِ ٱلرَّحۡمَٰنِ ٱلرَّحِيمِ",
			"author": "০. আল্লাহর নামে শুরু, যিনি পরম করুণাময়, সতত অসীম দয়ালু।"
		},
		{
			"_id": "5849",
			"sura": "83",
			"para": "30",
			"verses": "1",
			"names": "وَیۡلٌ   لِّلۡمُطَفِّفِیۡنَ ۙ﴿۱﴾ ",
			"number": "",
			"verses_PDMS": "وَیۡلٌ   لِّلۡمُطَفِّفِیۡنَ ۙ﴿۱﴾ ",
			"index": "5849",
			"name": "পরিমাপে কারচুপিকারীদের ধ্বংস অবধারিত,",
			"en_kanzulimaan": "Ruin is for the defrauders. (Those who measure less.)",
			"ur_kanzulimaan": "کم تولنے والوں کی خرابی ہے،",
			"hi_kanzulimaan": "कम तौलने वालों की ख़राबी है",
			"id": 1,
			"text": "وَیۡلٌ   لِّلۡمُطَفِّفِیۡنَ ۙ﴿۱﴾ ",
			"author": "১. ধ্বংস তাদের যারা মাপে বা ওজনে কম দেয়।"
		},
		{
			"_id": "5850",
			"sura": "83",
			"para": "30",
			"verses": "2",
			"names": "الَّذِیۡنَ  اِذَا  اکۡتَالُوۡا عَلَی النَّاسِ یَسۡتَوۡفُوۡنَ ۫﴿ۖ۲﴾ ",
			"number": "",
			"verses_PDMS": "الَّذِیۡنَ  اِذَا  اکۡتَالُوۡا عَلَی النَّاسِ یَسۡتَوۡفُوۡنَ ۫﴿ۖ۲﴾ ",
			"index": "5850",
			"name": "তারা যখন অপর লোকদের থেকে মেপে নেয়, তখন পুরোপুরিই নিয়ে থাকে, ",
			"en_kanzulimaan": "Those who when they take the measure from others, take it in full!",
			"ur_kanzulimaan": "وہ کہ جب اوروں سے ناپ لیں پورا لیں،",
			"hi_kanzulimaan": "वो कि जब औरों से माप लें पूरा लें",
			"id": 2,
			"text": "الَّذِیۡنَ  اِذَا  اکۡتَالُوۡا عَلَی النَّاسِ یَسۡتَوۡفُوۡنَ ۫﴿ۖ۲﴾ ",
			"author": "২. এরা যখন অন্যদের থেকে মেপে নেয়, তখন (তাদের থেকে) পূর্ণমাত্রায় নেয়।"
		},
		{
			"_id": "5851",
			"sura": "83",
			"para": "30",
			"verses": "3",
			"names": "وَ  اِذَا کَالُوۡہُمۡ  اَوۡ وَّزَنُوۡہُمۡ  یُخۡسِرُوۡنَ ﴿ؕ۳﴾ ",
			"number": "",
			"verses_PDMS": "وَ  اِذَا کَالُوۡہُمۡ  اَوۡ وَّزَنُوۡہُمۡ  یُخۡسِرُوۡنَ ﴿ؕ۳﴾ ",
			"index": "5851",
			"name": "আর যখন তাদেরকে মেপে ও ওজন করে দেয়, তখন কম দিয়ে থাকে।",
			"en_kanzulimaan": "Whereas when they give others after measuring or weighing, they give them less!",
			"ur_kanzulimaan": "اور جب انہیں ناپ تول کردی کم کردیں،",
			"hi_kanzulimaan": "और जब उनहें माप तौल कर दें कम कर दें",
			"id": 3,
			"text": "وَ  اِذَا کَالُوۡہُمۡ  اَوۡ وَّزَنُوۡہُمۡ  یُخۡسِرُوۡنَ ﴿ؕ۳﴾ ",
			"author": "৩. আর যখন নিজেরা অন্যকে মেপে দেয়, তখন কম দেয়।"
		},
		{
			"_id": "5852",
			"sura": "83",
			"para": "30",
			"verses": "4",
			"names": "اَلَا یَظُنُّ  اُولٰٓئِکَ اَنَّہُمۡ مَّبۡعُوۡثُوۡنَ ۙ﴿۴﴾ ",
			"number": "",
			"verses_PDMS": "اَلَا یَظُنُّ  اُولٰٓئِکَ اَنَّہُمۡ مَّبۡعُوۡثُوۡنَ ۙ﴿۴﴾ ",
			"index": "5852",
			"name": "ওই লোকদের কি এ বিশ্বাস নেই যে, তাদেরকে উঠতে হবে- ",
			"en_kanzulimaan": "What! Do they not expect that they will be raised?",
			"ur_kanzulimaan": "کیا ان لوگوں کو گمان نہیں کہ انہیں اٹھنا ہے،",
			"hi_kanzulimaan": "क्या इन लोगों के गुमान नहीं कि इन्हें उठना है",
			"id": 4,
			"text": "اَلَا یَظُنُّ  اُولٰٓئِکَ اَنَّہُمۡ مَّبۡعُوۡثُوۡنَ ۙ﴿۴﴾ ",
			"author": "৪. তারা কি এ কথায় বিশ্বাস করে না যে, তাদেরকে (মৃত্যুর পর) পুনরুত্থিত করা হবে,"
		},
		{
			"_id": "5853",
			"sura": "83",
			"para": "30",
			"verses": "5",
			"names": "لِیَوۡمٍ عَظِیۡمٍ ۙ﴿۵﴾ ",
			"number": "",
			"verses_PDMS": "لِیَوۡمٍ عَظِیۡمٍ ۙ﴿۵﴾ ",
			"index": "5853",
			"name": "এক মহান দিবসের জন্য?",
			"en_kanzulimaan": "(To be raised) for a Great Day?",
			"ur_kanzulimaan": "ایک عظمت والے دن کے لیے",
			"hi_kanzulimaan": "एक अज़मत वाले दिन के लिये (2फ)",
			"id": 5,
			"text": "لِیَوۡمٍ عَظِیۡمٍ ۙ﴿۵﴾ ",
			"author": "৫. এক ভয়াবহ দিনের জন্যে?"
		},
		{
			"_id": "5854",
			"sura": "83",
			"para": "30",
			"verses": "6",
			"names": "یَّوۡمَ یَقُوۡمُ النَّاسُ لِرَبِّ الۡعٰلَمِیۡنَ ؕ﴿۶﴾ ",
			"number": "",
			"verses_PDMS": "یَّوۡمَ یَقُوۡمُ النَّاسُ لِرَبِّ الۡعٰلَمِیۡنَ ؕ﴿۶﴾ ",
			"index": "5854",
			"name": "যেদিন সকল মানুষ রব্বুল আলামীনের দরবারে দণ্ডায়মান হবে!",
			"en_kanzulimaan": "The day when everyone will stand before the Lord Of The Creation.",
			"ur_kanzulimaan": "جس دن سب لوگ رب العالمین کے حضور کھڑے ہوں گے،",
			"hi_kanzulimaan": "जिस दिन सब लोग (3फ) सारे जगत के रब के हुज़ूर खङे होंगे",
			"id": 6,
			"text": "یَّوۡمَ یَقُوۡمُ النَّاسُ لِرَبِّ الۡعٰلَمِیۡنَ ؕ﴿۶﴾ ",
			"author": "৬. যেদিন সকল মানুষ সমগ্র জগতের প্রতিপালকের সমীপে দন্ডায়মান হবে।"
		},
		{
			"_id": "5855",
			"sura": "83",
			"para": "30",
			"verses": "7",
			"names": "کَلَّاۤ  اِنَّ  کِتٰبَ الۡفُجَّارِ لَفِیۡ  سِجِّیۡنٍ ؕ﴿۷﴾ ",
			"number": "",
			"verses_PDMS": "کَلَّاۤ  اِنَّ  کِتٰبَ الۡفُجَّارِ لَفِیۡ  سِجِّیۡنٍ ؕ﴿۷﴾ ",
			"index": "5855",
			"name": "নিশ্চয়, কাফিরদের লিপি সবচেয়ে নিম্নস্থান ‘সিজ্জীন’-এ রয়েছে। ",
			"en_kanzulimaan": "Indeed, the record of the disbelievers is in the lowest place, the Sijjeen.",
			"ur_kanzulimaan": "بیشک کافروں کی لکھت سب سے نیچی جگہ سجین میں ہے",
			"hi_kanzulimaan": "बेशक काफ़िरों की लिखत (4फ) सबसे नीची जगह सिज्जीन में है (5फ)",
			"id": 7,
			"text": "کَلَّاۤ  اِنَّ  کِتٰبَ الۡفُجَّارِ لَفِیۡ  سِجِّیۡنٍ ؕ﴿۷﴾ ",
			"author": "৭. এটি সত্য যে, পাপীদের আমলনামা আছে সিজ্জীনে (অর্থাৎ জাহান্নামের গভীর প্রকোষ্ঠে)।"
		},
		{
			"_id": "5856",
			"sura": "83",
			"para": "30",
			"verses": "8",
			"names": "وَ مَاۤ  اَدۡرٰىکَ مَا سِجِّیۡنٌ ؕ﴿۸﴾ ",
			"number": "",
			"verses_PDMS": "وَ مَاۤ  اَدۡرٰىکَ مَا سِجِّیۡنٌ ؕ﴿۸﴾ ",
			"index": "5856",
			"name": "এবং তুমি কি জানো ‘সিজ্জীন’ কেমন?",
			"en_kanzulimaan": "And what do you know, how (wretched) the Sijjeen is!",
			"ur_kanzulimaan": "اور تو کیا جانے سجین کیسی ہے",
			"hi_kanzulimaan": "और तू क्या जाने सिज्जीन कैसी है (6फ)",
			"id": 8,
			"text": "وَ مَاۤ  اَدۡرٰىکَ مَا سِجِّیۡنٌ ؕ﴿۸﴾ ",
			"author": "৮. আর আপনি কি জানেন, সিজ্জীন কী?"
		},
		{
			"_id": "5857",
			"sura": "83",
			"para": "30",
			"verses": "9",
			"names": "کِتٰبٌ مَّرۡقُوۡمٌ ؕ﴿۹﴾ ",
			"number": "",
			"verses_PDMS": "کِتٰبٌ مَّرۡقُوۡمٌ ؕ﴿۹﴾ ",
			"index": "5857",
			"name": "ওই লিপিখানা একটা মোহরকৃত লিপি।",
			"en_kanzulimaan": "The record is a sealed text.",
			"ur_kanzulimaan": "وہ لکھت ایک مہر کیا نوشتہ ہے",
			"hi_kanzulimaan": "वह लिखत एक मुहर किया लेखा है (7फ)",
			"id": 9,
			"text": "کِتٰبٌ مَّرۡقُوۡمٌ ؕ﴿۹﴾ ",
			"author": "৯. (এটি জাহান্নামের বন্দীখানার সে বড় প্রকোষ্ঠের ভিতর) লিখিত (এক) কিতাব (যাতে লিপিবদ্ধ রয়েছে সকল জাহান্নামীর নাম ও আমলনামা)।"
		},
		{
			"_id": "5858",
			"sura": "83",
			"para": "30",
			"verses": "10",
			"names": "وَیۡلٌ یَّوۡمَئِذٍ لِّلۡمُکَذِّبِیۡنَ ﴿ۙ۱۰﴾ ",
			"number": "",
			"verses_PDMS": "وَیۡلٌ یَّوۡمَئِذٍ لِّلۡمُکَذِّبِیۡنَ ﴿ۙ۱۰﴾ ",
			"index": "5858",
			"name": "ওই দিন অস্বীকারকারীদের জন্য ধ্বংস রয়েছে, ",
			"en_kanzulimaan": "Ruin is for the deniers on that day!",
			"ur_kanzulimaan": "اس دن جھٹلانے والوں کی خرابی ہے،",
			"hi_kanzulimaan": "उस दिन (8फ) झुटलाने वालों की ख़राबी है",
			"id": 10,
			"author": "১০. সে দিন সর্বনাশ হবে মিথ্যাপ্রতিপন্নকারীদের,",
			"text": "وَیۡلٌ یَّوۡمَئِذٍ لِّلۡمُکَذِّبِیۡنَ ﴿ۙ۱۰﴾ "
		},
		{
			"_id": "5859",
			"sura": "83",
			"para": "30",
			"verses": "11",
			"names": "الَّذِیۡنَ یُکَذِّبُوۡنَ بِیَوۡمِ الدِّیۡنِ ﴿ؕ۱۱﴾ ",
			"number": "",
			"verses_PDMS": "الَّذِیۡنَ یُکَذِّبُوۡنَ بِیَوۡمِ الدِّیۡنِ ﴿ؕ۱۱﴾ ",
			"index": "5859",
			"name": "যারা বিচার দিবসকে অস্বীকার করে।",
			"en_kanzulimaan": "Those who deny the Day of Justice.",
			"ur_kanzulimaan": "جو انصاف کے دن کو جھٹلاتے ہیں",
			"hi_kanzulimaan": "जो इनसाफ़ के दिन को झुटलाते हैं (9फ)",
			"id": 11,
			"text": "الَّذِیۡنَ یُکَذِّبُوۡنَ بِیَوۡمِ الدِّیۡنِ ﴿ؕ۱۱﴾ ",
			"author": "১১. যারা প্রতিদান দিবসকে মিথ্যাপ্রতিপন্ন করে,"
		},
		{
			"_id": "5860",
			"sura": "83",
			"para": "30",
			"verses": "12",
			"names": "وَ مَا یُکَذِّبُ بِہٖۤ  اِلَّا کُلُّ مُعۡتَدٍ اَثِیۡمٍ ﴿ۙ۱۲﴾ ",
			"number": "",
			"verses_PDMS": "وَ مَا یُکَذِّبُ بِہٖۤ  اِلَّا کُلُّ مُعۡتَدٍ اَثِیۡمٍ ﴿ۙ۱۲﴾ ",
			"index": "5860",
			"name": "এবং ওটা অস্বীকার করবে কেবল প্রত্যেক অবাধ্য;",
			"en_kanzulimaan": "And none will deny it, except every transgressor, rebel.",
			"ur_kanzulimaan": "اور اسے نہ جھٹلائے گا مگر ہر سرکش",
			"hi_kanzulimaan": "और उसे न झुटलाएगा मगर हर सरकश गुनाह गार (10फ)",
			"id": 12,
			"text": "وَ مَا یُکَذِّبُ بِہٖۤ  اِلَّا کُلُّ مُعۡتَدٍ اَثِیۡمٍ ﴿ۙ۱۲﴾ ",
			"author": "১২. আর কেউ তা মিথ্যাপ্রতিপন্ন করে না কেবল প্রত্যেক অবাধ্য ও পাপাচারী ব্যক্তি ব্যতীত।"
		},
		{
			"_id": "5861",
			"sura": "83",
			"para": "30",
			"verses": "13",
			"names": "اِذَا  تُتۡلٰی عَلَیۡہِ  اٰیٰتُنَا  قَالَ اَسَاطِیۡرُ الۡاَوَّلِیۡنَ ﴿ؕ۱۳﴾ ",
			"number": "",
			"verses_PDMS": "اِذَا  تُتۡلٰی عَلَیۡہِ  اٰیٰتُنَا  قَالَ اَسَاطِیۡرُ الۡاَوَّلِیۡنَ ﴿ؕ۱۳﴾ ",
			"index": "5861",
			"name": "যখন তার উপর আমার আয়াতগুলো পাঠ করা হয়, তখন বলে, ‘(এগুলো হচ্ছে) পূর্ববর্তীদের কাহিনী। ",
			"en_kanzulimaan": "When you recite Our verses to him, he says, Stories of earlier men!",
			"ur_kanzulimaan": "جب اس پر ہماری آیتیں پڑھی جائیں کہے اگلوں کی کہانیاں ہیں،",
			"hi_kanzulimaan": "जब उसपर हमारी आयतें पढ़ी जाएं कहे (11फ) अगलों की कहानियाँ हैं",
			"id": 13,
			"text": "اِذَا  تُتۡلٰی عَلَیۡہِ  اٰیٰتُنَا  قَالَ اَسَاطِیۡرُ الۡاَوَّلِیۡنَ ﴿ؕ۱۳﴾ ",
			"author": "১৩. যখন তাকে আমাদের আয়াতসমূহ পাঠ করে শোনানো হয়, তখন সে বলে (অথবা ভাবে), ‘(এ তো) আগেকার লোকেদের গল্পকাহিনী’।"
		},
		{
			"_id": "5862",
			"sura": "83",
			"para": "30",
			"verses": "14",
			"names": "کَلَّا بَلۡ ٜ رَانَ عَلٰی قُلُوۡبِہِمۡ مَّا کَانُوۡا یَکۡسِبُوۡنَ ﴿۱۴﴾ ",
			"number": "",
			"verses_PDMS": "کَلَّا بَلۡ ٜ رَانَ عَلٰی قُلُوۡبِہِمۡ مَّا کَانُوۡا یَکۡسِبُوۡنَ ﴿۱۴﴾ ",
			"index": "5862",
			"name": "কিছুই নয়, বরং তাদের অন্তরগুলোর উপর মরিচা লেপন করে দিয়েছে তাদের কৃতকর্মগুলো। ",
			"en_kanzulimaan": "Not at all  but rather their earnings have heaped rust upon their hearts.",
			"ur_kanzulimaan": "کوئی نہیں بلکہ ان کے دلوں پر زنگ چڑھادیا ہے ان کی کمائیوں نے",
			"hi_kanzulimaan": "कोई नहीं (12फ) बल्कि उनके दिलों पर ज़ंग चढ़ा दिया है उनकी कमाइयों ने (13फ)",
			"id": 14,
			"text": "کَلَّا بَلۡ ٜ رَانَ عَلٰی قُلُوۡبِہِمۡ مَّا کَانُوۡا یَکۡسِبُوۡنَ ﴿۱۴﴾ ",
			"author": "১৪. (তা) কখনোই নয়, বরং (বাস্তবতা তো এই যে) তাদের অন্তরে তাদের অর্জিত (মন্দ) আমলের মরিচার আস্তর পড়ে গেছে (ফলে আয়াতসমূহ তাদের অন্তরে প্রভাব বিস্তার করে না)।"
		},
		{
			"_id": "5863",
			"sura": "83",
			"para": "30",
			"verses": "15",
			"names": "کَلَّاۤ  اِنَّہُمۡ عَنۡ رَّبِّہِمۡ یَوۡمَئِذٍ لَّمَحۡجُوۡبُوۡنَ ﴿ؕ۱۵﴾ ",
			"number": "",
			"verses_PDMS": "کَلَّاۤ  اِنَّہُمۡ عَنۡ رَّبِّہِمۡ یَوۡمَئِذٍ لَّمَحۡجُوۡبُوۡنَ ﴿ؕ۱۵﴾ ",
			"index": "5863",
			"name": "হাঁ, হাঁ, নিশ্চয় ওই দিন তারা স্বীয় রবের সাক্ষাৎ থেকে বঞ্চিত;",
			"en_kanzulimaan": "Yes indeed  they will be deprived of seeing their Lord on that day.",
			"ur_kanzulimaan": "ہاں ہاں بیشک وہ اس دن اپنے رب کے دیدار سے محروم ہیں",
			"hi_kanzulimaan": "हाँ हाँ बेशक वो उस दिन (14फ) अपने रब के दीदार से मेहरूम हैं (15फ)",
			"id": 15,
			"text": "کَلَّاۤ  اِنَّہُمۡ عَنۡ رَّبِّہِمۡ یَوۡمَئِذٍ لَّمَحۡجُوۡبُوۡنَ ﴿ؕ۱۵﴾ ",
			"author": "১৫. সত্য এ যে, নিশ্চয়ই সেদিন তাদেরকে তাদের প্রতিপালকের দিদার থেকে (বঞ্চিত করতে) পর্দার অন্তরাল করে দেয়া হবে।"
		},
		{
			"_id": "5864",
			"sura": "83",
			"para": "30",
			"verses": "16",
			"names": "ثُمَّ  اِنَّہُمۡ  لَصَالُوا الۡجَحِیۡمِ ﴿ؕ۱۶﴾ ",
			"number": "",
			"verses_PDMS": "ثُمَّ  اِنَّہُمۡ  لَصَالُوا الۡجَحِیۡمِ ﴿ؕ۱۶﴾ ",
			"index": "5864",
			"name": "অতঃপর নিশ্চয় তাদেরকে জাহান্নামে প্রবেশ করতে হবে;",
			"en_kanzulimaan": "Then indeed they have to enter hell.",
			"ur_kanzulimaan": "پھر بیشک انہیں جہنم میں داخل ہونا،",
			"hi_kanzulimaan": "फिर बेशक उन्हें जहन्नम दाख़िल होना",
			"id": 16,
			"text": "ثُمَّ  اِنَّہُمۡ  لَصَالُوا الۡجَحِیۡمِ ﴿ؕ۱۶﴾ ",
			"author": "১৬. তারপর তারা জাহান্নামে নিক্ষিপ্ত হবে।"
		},
		{
			"_id": "5865",
			"sura": "83",
			"para": "30",
			"verses": "17",
			"names": "ثُمَّ یُقَالُ ہٰذَا الَّذِیۡ کُنۡتُمۡ بِہٖ تُکَذِّبُوۡنَ ﴿ؕ۱۷﴾ ",
			"number": "",
			"verses_PDMS": "ثُمَّ یُقَالُ ہٰذَا الَّذِیۡ کُنۡتُمۡ بِہٖ تُکَذِّبُوۡنَ ﴿ؕ۱۷﴾ ",
			"index": "5865",
			"name": "তারপর (তাদেরকে) বলা হবে, ‘এ হচ্ছে তা-ই, যাকে তোমরা অস্বীকার করতে’।",
			"en_kanzulimaan": "It will then be said, This is what you used to deny.",
			"ur_kanzulimaan": "پھر کہا جائے گا، یہ ہے وہ جسے تم جھٹلاتے تھے",
			"hi_kanzulimaan": "फिर कहा जाएगा यह है वह (16फ) जिसे तुम झुटलाते थे (17फ)",
			"id": 17,
			"text": "ثُمَّ یُقَالُ ہٰذَا الَّذِیۡ کُنۡتُمۡ بِہٖ تُکَذِّبُوۡنَ ﴿ؕ۱۷﴾ ",
			"author": "১৭. তারপর তাদেরকে বলা হবে: ‘এটিই (জাহান্নামের আযাব) যা তোমরা অস্বীকার করতে’।"
		},
		{
			"_id": "5866",
			"sura": "83",
			"para": "30",
			"verses": "18",
			"names": "کَلَّاۤ  اِنَّ  کِتٰبَ الۡاَبۡرَارِ لَفِیۡ عِلِّیِّیۡنَ ﴿ؕ۱۸﴾ ",
			"number": "",
			"verses_PDMS": "کَلَّاۤ  اِنَّ  کِتٰبَ الۡاَبۡرَارِ لَفِیۡ عِلِّیِّیۡنَ ﴿ؕ۱۸﴾ ",
			"index": "5866",
			"name": "হাঁ, হাঁ, নিশ্চয়, পুণ্যবানদের লিপি সবচেয়ে উচ্চস্থান ‘ইল্লিয়্যীন’এ- রয়েছে;।",
			"en_kanzulimaan": "Indeed the record of the virtuous is in the highest place, the Illiyin.",
			"ur_kanzulimaan": "ہاں ہاں بیشک نیکوں کی لکھت سب سے اونچا محل علیین میں ہے",
			"hi_kanzulimaan": "हाँ हाँ बेशक नेकों की लिखत (18फ) सब से ऊंचा महल इल्लीयीन में है (19फ)",
			"id": 18,
			"text": "کَلَّاۤ  اِنَّ  کِتٰبَ الۡاَبۡرَارِ لَفِیۡ عِلِّیِّیۡنَ ﴿ؕ۱۸﴾ ",
			"author": "১৮. এ (ও) সত্য যে নিশ্চয়ই পূণ্যবানদের আমলনামা আছে ইল্লিয়্যিনে (অর্থাৎ জান্নাতের উপকক্ষে)।"
		},
		{
			"_id": "5867",
			"sura": "83",
			"para": "30",
			"verses": "19",
			"names": "وَ مَاۤ  اَدۡرٰىکَ مَا عِلِّیُّوۡنَ ﴿ؕ۱۹﴾ ",
			"number": "",
			"verses_PDMS": "وَ مَاۤ  اَدۡرٰىکَ مَا عِلِّیُّوۡنَ ﴿ؕ۱۹﴾ ",
			"index": "5867",
			"name": "এবং তুমি কি জানো ‘ইল্লিয়্যীন’ কেমন?",
			"en_kanzulimaan": "And what do you know what the Illiyoon are!",
			"ur_kanzulimaan": "اور تو کیا جانے علیین کیسی ہے",
			"hi_kanzulimaan": "और तू क्या जाने इल्लीयीन कैसी है (20फ)",
			"id": 19,
			"text": "وَ مَاۤ  اَدۡرٰىکَ مَا عِلِّیُّوۡنَ ﴿ؕ۱۹﴾ ",
			"author": "১৯. আর আপনি কি জানেন, ইল্লিয়্যিন কী?"
		},
		{
			"_id": "5868",
			"sura": "83",
			"para": "30",
			"verses": "20",
			"names": "کِتٰبٌ مَّرۡقُوۡمٌ ﴿ۙ۲۰﴾ ",
			"number": "",
			"verses_PDMS": "کِتٰبٌ مَّرۡقُوۡمٌ ﴿ۙ۲۰﴾ ",
			"index": "5868",
			"name": "ওই লিপিটা হচ্ছে একটা মোহরকৃত লিপি;",
			"en_kanzulimaan": "The record is a sealed text.",
			"ur_kanzulimaan": "وہ لکھت ایک مہر کیا نوشتہ ہے",
			"hi_kanzulimaan": "वह लिखत एक मुहर किया लेखा है (21फ)",
			"id": 20,
			"text": "کِتٰبٌ مَّرۡقُوۡمٌ ﴿ۙ۲۰﴾ ",
			"author": "২০.(এটি জান্নাতের সুউচ্চ প্রাসাদে সুবিশাল উপকক্ষে) লিপিবদ্ধ (এক) কিতাব (যাতে সেসব জান্নাতির নাম ও নেক আমলনামাসমূহ লিপিবদ্ধ রয়েছে, যাদেরকে উচ্চতর স্থান প্রদান করা হবে)।"
		},
		{
			"_id": "5869",
			"sura": "83",
			"para": "30",
			"verses": "21",
			"names": "یَّشۡہَدُہُ  الۡمُقَرَّبُوۡنَ ﴿ؕ۲۱﴾ ",
			"number": "",
			"verses_PDMS": "یَّشۡہَدُہُ  الۡمُقَرَّبُوۡنَ ﴿ؕ۲۱﴾ ",
			"index": "5869",
			"name": "নৈকট্যপ্রাপ্তরা যার যিয়ারত করে। ",
			"en_kanzulimaan": "Which is witnessed by the close ones.",
			"ur_kanzulimaan": "کہ مقرب جس کی زیارت کرتے ہیں،",
			"hi_kanzulimaan": "कि नज़्दीकी वाले (22फ) जिसकी ज़ियारत करते है",
			"id": 21,
			"text": "یَّشۡہَدُہُ  الۡمُقَرَّبُوۡنَ ﴿ؕ۲۱﴾ ",
			"author": "২১. সেখানে (আল্লাহ্‌র) নৈকট্যপ্রাপ্ত ফেরেশতারা উপস্থিত থাকেন।"
		},
		{
			"_id": "5870",
			"sura": "83",
			"para": "30",
			"verses": "22",
			"names": "اِنَّ  الۡاَبۡرَارَ لَفِیۡ نَعِیۡمٍ ﴿ۙ۲۲﴾ ",
			"number": "",
			"verses_PDMS": "اِنَّ  الۡاَبۡرَارَ لَفِیۡ نَعِیۡمٍ ﴿ۙ۲۲﴾ ",
			"index": "5870",
			"name": "নিশ্চয় পুণ্যবান অবশ্য শান্তিতে থাকে, ",
			"en_kanzulimaan": "Indeed the virtuous are in serenity.",
			"ur_kanzulimaan": "بیشک نیکوکار ضرور چین میں ہیں،",
			"hi_kanzulimaan": "बेशक नेकी वाले ज़रूर चैन में हैं",
			"id": 22,
			"text": "اِنَّ  الۡاَبۡرَارَ لَفِیۡ نَعِیۡمٍ ﴿ۙ۲۲﴾ ",
			"author": "২২. নিশ্চয়ই পূণ্যবানগণ থাকবেন (শান্তি ও আনন্দের) নিয়ামতপূর্ণ জান্নাতে,"
		},
		{
			"_id": "5871",
			"sura": "83",
			"para": "30",
			"verses": "23",
			"names": "عَلَی الۡاَرَآئِکِ یَنۡظُرُوۡنَ ﴿ۙ۲۳﴾ ",
			"number": "",
			"verses_PDMS": "عَلَی الۡاَرَآئِکِ یَنۡظُرُوۡنَ ﴿ۙ۲۳﴾ ",
			"index": "5871",
			"name": "তখ্‌তসমূহের উপর (বসে) দেখে। ",
			"en_kanzulimaan": "On thrones, watching.",
			"ur_kanzulimaan": "تختوں پر دیکھتے ہیں",
			"hi_kanzulimaan": "तख़्तों पर देखते हैं (23फ)",
			"id": 23,
			"text": "عَلَی الۡاَرَآئِکِ یَنۡظُرُوۡنَ ﴿ۙ۲۳﴾ ",
			"author": "২৩. আসনে উপবিষ্ট হয়ে তারা অবলোকন করবেন।"
		},
		{
			"_id": "5872",
			"sura": "83",
			"para": "30",
			"verses": "24",
			"names": "تَعۡرِفُ فِیۡ  وُجُوۡہِہِمۡ نَضۡرَۃَ  النَّعِیۡمِ ﴿ۚ۲۴﴾ ",
			"number": "",
			"verses_PDMS": "تَعۡرِفُ فِیۡ  وُجُوۡہِہِمۡ نَضۡرَۃَ  النَّعِیۡمِ ﴿ۚ۲۴﴾ ",
			"index": "5872",
			"name": "তুমি তাদের চেহারাগুলোর উপর স্বস্তির সজীবতা বুঝতে পারবে, ",
			"en_kanzulimaan": "You will recognise the freshness of serenity on their faces.",
			"ur_kanzulimaan": "تو ان کے چہروں میں چین کی تازگی پہنچانے",
			"hi_kanzulimaan": "तू उनके चेहरों में चैन की ताज़गी पहचाने (24फ)",
			"id": 24,
			"text": "تَعۡرِفُ فِیۡ  وُجُوۡہِہِمۡ نَضۡرَۃَ  النَّعِیۡمِ ﴿ۚ۲۴﴾ ",
			"author": "২৪. আপনি তাদের চেহারাতেই নিয়ামত ও প্রশান্তির শোভা ও প্রস্ফুটন দেখতে পাবেন।"
		},
		{
			"_id": "5873",
			"sura": "83",
			"para": "30",
			"verses": "25",
			"names": "یُسۡقَوۡنَ مِنۡ  رَّحِیۡقٍ مَّخۡتُوۡمٍ ﴿ۙ۲۵﴾ ",
			"number": "",
			"verses_PDMS": "یُسۡقَوۡنَ مِنۡ  رَّحِیۡقٍ مَّخۡتُوۡمٍ ﴿ۙ۲۵﴾ ",
			"index": "5873",
			"name": "বিশুদ্ধ পানীয় পান করানো হবে, যা মোহরকৃত অবস্থায় রাখা হয়েছে;",
			"en_kanzulimaan": "They will be given pure wine to drink, which is kept preserved, sealed.",
			"ur_kanzulimaan": "نتھری شراب پلائے جائیں گے جو مہُر کی ہوئی رکھی ہے",
			"hi_kanzulimaan": "निथरी शराब पिलाई जाएंगे जो मुहर की हुई रखी है (25फ)",
			"id": 25,
			"text": "یُسۡقَوۡنَ مِنۡ  رَّحِیۡقٍ مَّخۡتُوۡمٍ ﴿ۙ۲۵﴾ ",
			"author": "২৫. তাদেরকে মোহরাঙ্কিত খুবই সুস্বাদু, পবিত্র পানীয় পান করানো হবে।"
		},
		{
			"_id": "5874",
			"sura": "83",
			"para": "30",
			"verses": "26",
			"names": "خِتٰمُہٗ  مِسۡکٌ ؕ وَ فِیۡ ذٰلِکَ فَلۡیَتَنَافَسِ الۡمُتَنَافِسُوۡنَ ﴿ؕ۲۶﴾ ",
			"number": "",
			"verses_PDMS": "خِتٰمُہٗ  مِسۡکٌ ؕ وَ فِیۡ ذٰلِکَ فَلۡیَتَنَافَسِ الۡمُتَنَافِسُوۡنَ ﴿ؕ۲۶﴾ ",
			"index": "5874",
			"name": "এর মোহর হচ্ছে কস্তুরীর উপর এবং এরই উপর চাই আকাঙ্ক্ষাকারীদের আকাঙ্ক্ষা করা। ",
			"en_kanzulimaan": "Its seal is upon musk; and for this should those who crave be eager.",
			"ur_kanzulimaan": "اس کی مہُر مشک پر ہے، اور اسی پر چاہیے کہ للچائیں للچانے والے",
			"hi_kanzulimaan": "की मुहर मुश्क पर है, और उसी पर चाहिये कि ललचाएं ललचाने वाले (26फ)",
			"id": 26,
			"text": "خِتٰمُہٗ  مِسۡکٌ ؕ وَ فِیۡ ذٰلِکَ فَلۡیَتَنَافَسِ الۡمُتَنَافِسُوۡنَ ﴿ؕ۲۶﴾ ",
			"author": "২৬. এর মোহর হবে কস্তুরীর। আর (এই সেই শরাব) যা অর্জনে আকাঙ্ক্ষীগণের দ্রুত প্রচেষ্টার মাধ্যমে অগ্রসর হওয়া উচিত (কেউ নিয়ামতের শরাবের অনুসন্ধানী ও আগ্রহী, কেউ নৈকট্যের শরাবের, আবার কেউ দিদারের শরাবের, প্রত্যেককেই তাদের আকাঙ্ক্ষা মোতাবেক পান করানো হবে)।"
		},
		{
			"_id": "5875",
			"sura": "83",
			"para": "30",
			"verses": "27",
			"names": "وَ مِزَاجُہٗ  مِنۡ تَسۡنِیۡمٍ ﴿ۙ۲۷﴾ ",
			"number": "",
			"verses_PDMS": "وَ مِزَاجُہٗ  مِنۡ تَسۡنِیۡمٍ ﴿ۙ۲۷﴾ ",
			"index": "5875",
			"name": "এবং তার মিশ্রণ হচ্ছে ‘তাসনীম’-এর সাথে,",
			"en_kanzulimaan": "And it is mixed with Tasneem.",
			"ur_kanzulimaan": "اور اس کی ملونی تسنیم سے ہے",
			"hi_kanzulimaan": "और उसकी मिलौनी तस्नीम से है (27फ)",
			"id": 27,
			"text": "وَ مِزَاجُہٗ  مِنۡ تَسۡنِیۡمٍ ﴿ۙ۲۷﴾ ",
			"author": "২৭. আর এতে (এ শরাবে) থাকবে তাসনীমের পানির মিশ্রন।"
		},
		{
			"_id": "5876",
			"sura": "83",
			"para": "30",
			"verses": "28",
			"names": "عَیۡنًا یَّشۡرَبُ بِہَا الۡمُقَرَّبُوۡنَ ﴿ؕ۲۸﴾ ",
			"number": "",
			"verses_PDMS": "عَیۡنًا یَّشۡرَبُ بِہَا الۡمُقَرَّبُوۡنَ ﴿ؕ۲۸﴾ ",
			"index": "5876",
			"name": "সেই ঝরণা, যা থেকে (আল্লাহ্‌র) নৈকট্যপ্রাপ্তরা পান করেন। ",
			"en_kanzulimaan": "The spring from which drink the ones close to Allah.",
			"ur_kanzulimaan": "وہ چشمہ جس سے مقربانِ بارگاہ پیتے ہیں",
			"hi_kanzulimaan": "वह चश्मा जिससे नज़्दीकी वाले पीते हैं (28फ)",
			"id": 28,
			"text": "عَیۡنًا یَّشۡرَبُ بِہَا الۡمُقَرَّبُوۡنَ ﴿ؕ۲۸﴾ ",
			"author": "২৮. (এ তাসনীম) একটি ঝরনা, যা থেকে কেবলমাত্র নৈকট্যপ্রাপ্তরা পান করে।"
		},
		{
			"_id": "5877",
			"sura": "83",
			"para": "30",
			"verses": "29",
			"names": "اِنَّ  الَّذِیۡنَ اَجۡرَمُوۡا کَانُوۡا مِنَ الَّذِیۡنَ اٰمَنُوۡا یَضۡحَکُوۡنَ ﴿۫ۖ۲۹﴾ ",
			"number": "",
			"verses_PDMS": "اِنَّ  الَّذِیۡنَ اَجۡرَمُوۡا کَانُوۡا مِنَ الَّذِیۡنَ اٰمَنُوۡا یَضۡحَکُوۡنَ ﴿۫ۖ۲۹﴾ ",
			"index": "5877",
			"name": "নিশ্চয় দোষী ব্যক্তিরা ঈমানদারদের নিয়ে হাস্য করতো, ",
			"en_kanzulimaan": "Indeed the guilty used to laugh at the believers.",
			"ur_kanzulimaan": "بیشک مجرم لوگ ایمان والوں سے ہنسا کرتے تھے،",
			"hi_kanzulimaan": "बेशक मुजरिम लोग (29फ) ईमान वालों से (30फ) हंसा करते थे",
			"id": 29,
			"text": "اِنَّ  الَّذِیۡنَ اَجۡرَمُوۡا کَانُوۡا مِنَ الَّذِیۡنَ اٰمَنُوۡا یَضۡحَکُوۡنَ ﴿۫ۖ۲۹﴾ ",
			"author": "২৯. নিশ্চয়ই অপরাধীরা ঈমানদারগণকে (পৃথিবীতে) ঠাট্টা বিদ্রুপ করতো।"
		},
		{
			"_id": "5878",
			"sura": "83",
			"para": "30",
			"verses": "30",
			"names": "وَ اِذَا  مَرُّوۡا بِہِمۡ یَتَغَامَزُوۡنَ ﴿۫ۖ۳۰﴾ ",
			"number": "",
			"verses_PDMS": "وَ اِذَا  مَرُّوۡا بِہِمۡ یَتَغَامَزُوۡنَ ﴿۫ۖ۳۰﴾ ",
			"index": "5878",
			"name": "আর যহন তারা (মু’মিনগণ) তাদের (কাফিরগণ) পার্শ্ব দিয়ে অতিক্রম করতো তখন তারা (কাফিরগণ) একে অপরকে তাদের (ঈমানদারগণ) প্রতি চোখ দিয়ে ইশারা করতো। ",
			"en_kanzulimaan": "And when the believers used to pass by, they used to gesture at each other with their eyes.",
			"ur_kanzulimaan": "اور جب وہ ان پر گزرتے تو یہ آپس میں ان پر آنکھوں سے اشارے کرتے",
			"hi_kanzulimaan": "और जब वो (31फ) उनपर गुज़रते तो ये आपस में उनपर आँखों से इशारे करते (32फ)",
			"id": 30,
			"text": "وَ اِذَا  مَرُّوۡا بِہِمۡ یَتَغَامَزُوۡنَ ﴿۫ۖ۳۰﴾ ",
			"author": "৩০. আর যখন তাদের পাশ দিয়ে যেতো, তখন নিজেদের মধ্যে চক্ষু টিপে ইশারা করতো।"
		},
		{
			"_id": "5879",
			"sura": "83",
			"para": "30",
			"verses": "31",
			"names": "وَ اِذَا  انۡقَلَبُوۡۤا  اِلٰۤی  اَہۡلِہِمُ  انۡقَلَبُوۡا فَکِہِیۡنَ ﴿۫ۖ۳۱﴾ ",
			"number": "",
			"verses_PDMS": "وَ اِذَا  انۡقَلَبُوۡۤا  اِلٰۤی  اَہۡلِہِمُ  انۡقَلَبُوۡا فَکِہِیۡنَ ﴿۫ۖ۳۱﴾ ",
			"index": "5879",
			"name": "এবং যখন আপন ঘরের দিকে প্রত্যাবর্তন করতো, (তখন) তারা আনন্দ করতে করতে ফিরতো,",
			"en_kanzulimaan": "And whilst returning to their homes, they used to return rejoicing.",
			"ur_kanzulimaan": "اور جب (ف۹۳۳ اپنے گھر پلٹتے خوشیاں کرتے پلٹتے",
			"hi_kanzulimaan": "और जब (33फ) अपने घर पलटते ख़ुशियाँ करते पलटते (34फ)",
			"id": 31,
			"text": "وَ اِذَا  انۡقَلَبُوۡۤا  اِلٰۤی  اَہۡلِہِمُ  انۡقَلَبُوۡا فَکِہِیۡنَ ﴿۫ۖ۳۱﴾ ",
			"author": "৩১. আর যখন তারা নিজেদের পরিবারের মধ্যে ফিরে যেত, তখন (মুমিন বান্দাদের অভাব-অনটন এবং নিজেদের স্বচ্ছলতার মধ্যে তুলনা করে) অহংকার প্রদর্শন করতো এবং বিদ্রুপ করতে করতে ফিরে যেত।"
		},
		{
			"_id": "5880",
			"sura": "83",
			"para": "30",
			"verses": "32",
			"names": "وَ اِذَا رَاَوۡہُمۡ قَالُوۡۤا اِنَّ ہٰۤؤُلَآءِ لَضَآلُّوۡنَ ﴿ۙ۳۲﴾ ",
			"number": "",
			"verses_PDMS": "وَ اِذَا رَاَوۡہُمۡ قَالُوۡۤا اِنَّ ہٰۤؤُلَآءِ لَضَآلُّوۡنَ ﴿ۙ۳۲﴾ ",
			"index": "5880",
			"name": "আর যখন মুসলমানদেরকে দেখতো, তখন বলতো, ‘নিশ্চয় এসব লোক পথভ্রষ্ট’।",
			"en_kanzulimaan": "And upon seeing the Muslims, they used to say, Indeed they have gone astray.",
			"ur_kanzulimaan": "اور جب مسلمانوں کو دیکھتے کہتے بیشک یہ لوگ بہکے ہوئے ہیں",
			"hi_kanzulimaan": "और जब मुसलमानों को देखते कहते बेशक ये लोग बहके हुए हैं (35फ)",
			"id": 32,
			"text": "وَ اِذَا رَاَوۡہُمۡ قَالُوۡۤا اِنَّ ہٰۤؤُلَآءِ لَضَآلُّوۡنَ ﴿ۙ۳۲﴾ ",
			"author": "৩২.আর যখন তারা (অর্থাৎ উদ্ধত লোকেরা) এদেরকে (এ দৈন্যপীড়িত মুমিনদেরকে) দেখতো, তখন বলতো: ‘নিশ্চয়ই এই লোকেরা পথভ্রষ্ট হয়ে গিয়েছে’ (অর্থাৎ এরা দুনিয়া হারিয়ে ফেলেছে আর আখিরাত তো কেবলই এক কল্পকাহিনী)।"
		},
		{
			"_id": "5881",
			"sura": "83",
			"para": "30",
			"verses": "33",
			"names": "وَ  مَاۤ  اُرۡسِلُوۡا عَلَیۡہِمۡ  حٰفِظِیۡنَ ﴿ؕ۳۳﴾ ",
			"number": "",
			"verses_PDMS": "وَ  مَاۤ  اُرۡسِلُوۡا عَلَیۡہِمۡ  حٰفِظِیۡنَ ﴿ؕ۳۳﴾ ",
			"index": "5881",
			"name": "এবং এরা এদের (মুমিনগণ) জন্য কোন হিফাযতকারী হিসেবে প্রেরিত হয় নি।",
			"en_kanzulimaan": "Whereas they have not at all been sent as guardians over them.",
			"ur_kanzulimaan": "اور یہ کچھ ان پر نگہبان بناکر نہ بھیجے گئے",
			"hi_kanzulimaan": "और ये (36फ) कुछ उन पर निगहबान बना कर न भेजे गए (37फ)",
			"id": 33,
			"text": "وَ  مَاۤ  اُرۡسِلُوۡا عَلَیۡہِمۡ  حٰفِظِیۡنَ ﴿ؕ۳۳﴾ ",
			"author": "৩৩.অথচ তারা তাদের (অবস্থার) উপর তত্ত্বাবধায়করূপে প্রেরিত হয়নি।"
		},
		{
			"_id": "5882",
			"sura": "83",
			"para": "30",
			"verses": "34",
			"names": "فَالۡیَوۡمَ الَّذِیۡنَ اٰمَنُوۡا مِنَ الۡکُفَّارِ یَضۡحَکُوۡنَ ﴿ۙ۳۴﴾  ",
			"number": "",
			"verses_PDMS": "فَالۡیَوۡمَ الَّذِیۡنَ اٰمَنُوۡا مِنَ الۡکُفَّارِ یَضۡحَکُوۡنَ ﴿ۙ۳۴﴾  ",
			"index": "5882",
			"name": "সুতরাং আজ ঈমানদারগণ কাফিরদের প্রতি হাসছে, ",
			"en_kanzulimaan": "So this day it is the believers who laugh at the disbelievers.",
			"ur_kanzulimaan": "تو آج ایمان والے کافروں سے ہنستے ہیں",
			"hi_kanzulimaan": "तो आज (38फ) ईमान वाले काफ़िरों से हंसते हैं (39फ)",
			"id": 34,
			"text": "فَالۡیَوۡمَ الَّذِیۡنَ اٰمَنُوۡا مِنَ الۡکُفَّارِ یَضۡحَکُوۡنَ ﴿ۙ۳۴﴾  ",
			"author": "৩৪. অতঃপর (দেখো) আজ ঈমানদারগণ কাফেরদের প্রতি হাসছে।"
		},
		{
			"_id": "5883",
			"sura": "83",
			"para": "30",
			"verses": "35",
			"names": "عَلَی الۡاَرَآئِکِ ۙ یَنۡظُرُوۡنَ ﴿ؕ۳۵﴾ ",
			"number": "",
			"verses_PDMS": "عَلَی الۡاَرَآئِکِ ۙ یَنۡظُرُوۡنَ ﴿ؕ۳۵﴾ ",
			"index": "5883",
			"name": "তখ্‌তগুলোর উপর উপবিষ্ট হয়ে দেখছে। ",
			"en_kanzulimaan": "On high thrones, watching.",
			"ur_kanzulimaan": "تختوں پر بیٹھے دیکھتے ہیں",
			"hi_kanzulimaan": "तख़्तों पर बैठे देखते हैं (40फ)",
			"id": 35,
			"text": "عَلَی الۡاَرَآئِکِ ۙ یَنۡظُرُوۡنَ ﴿ؕ۳۵﴾ ",
			"author": "৩৫. সুসজ্জিত আসনে বসে (নিজেদের সাফল্য আর কাফেরদের ব্যর্থতা) অবলোকন করছে।"
		},
		{
			"_id": "5884",
			"sura": "83",
			"para": "30",
			"verses": "36",
			"names": "ہَلۡ  ثُوِّبَ الۡکُفَّارُ  مَا کَانُوۡا یَفۡعَلُوۡنَ ﴿۳۶﴾",
			"number": "",
			"verses_PDMS": "ہَلۡ  ثُوِّبَ الۡکُفَّارُ  مَا کَانُوۡا یَفۡعَلُوۡنَ ﴿۳۶﴾",
			"index": "5884",
			"name": "কেন? কাফিরদের নিজ কৃতকর্মের কিছু প্রতিদান মিলেছে তো!",
			"en_kanzulimaan": "Did not the disbelievers get repaid for what they used to do?",
			"ur_kanzulimaan": "کیوں کچھ بدلا ملا کافروں کو اپنے کیے کا",
			"hi_kanzulimaan": "क्यों कुछ बदला मिला काफ़िरों को अपने किये का (41फ)",
			"id": 36,
			"text": "ہَلۡ  ثُوِّبَ الۡکُفَّارُ  مَا کَانُوۡا یَفۡعَلُوۡنَ ﴿٪۳۶﴾\n‎ 1 رُكوع",
			"author": "৩৬. তবে কি কাফেরদেরকে সে সবের (অর্থাৎ সে সব ঠাট্টা-বিদ্রুপের) পরিপূর্ণ প্রতিদান দিয়ে দেয়া হয়েছে, যা তারা (মুমিনদের প্রতি) করতো?"
		}
	]